{
  "id": "returning_to_the_burning_school_gym",
  "name": "Returning to the Burning School Gym",
  "description": "The flames rage anew! The masterminds behind this chaos, Infernal Ibuki and Infernal Raiden, await in the restored inferno.",
  "difficulty": 9,
  "objectives": {
    "winConditions": [
      { "type": "allEnemiesDefeated" }
    ]
  },
  "stageEffects": [
    {
      "id": "burning_ground",
      "name": "Burning Ground",
      "description": "The player's side is burning, dealing 200 damage each turn to player characters.",
      "icon": "Icons/effects/burning_ground.png"
    }
  ],
  "enemies": [
    {
      "characterId": "infernal_ibuki"
    },
    {
        "characterId": "infernal_raiden"
    }
  ],
  "rewards": [
    {
      "type": "gold",
      "value": 1000
    },
    {
      "type": "xp",
      "value": 500
    }
  ],
  "backgroundImage": "images/stages/burning_school_gym.png",
  "backgroundMusic": "sounds/bgaudio6.mp3"
} 